{"allContent":{"docusaurus-plugin-content-docs":{"default":{"loadedVersions":[{"versionName":"current","label":"Next","banner":null,"badge":false,"noIndex":false,"className":"docs-version-current","path":"/tts-wrapper/docs","tagsPath":"/tts-wrapper/docs/tags","editUrl":"https://github.com/willwade/tts-wrapper/tree/main/website/docs","editUrlLocalized":"https://github.com/willwade/tts-wrapper/tree/main/website/i18n/en/docusaurus-plugin-content-docs/current","isLast":true,"routePriority":-1,"sidebarFilePath":"/Users/willwade/GitHub/tts-wrapper/website/sidebars.js","contentPath":"/Users/willwade/GitHub/tts-wrapper/website/docs","contentPathLocalized":"/Users/willwade/GitHub/tts-wrapper/website/i18n/en/docusaurus-plugin-content-docs/current","docs":[{"id":"api/overview","title":"API Overview","description":"TTS Wrapper's API is designed to be intuitive and consistent across different TTS engines. This overview will help you understand the main components and their relationships.","source":"@site/docs/api/overview.md","sourceDirName":"api","slug":"/api/overview","permalink":"/tts-wrapper/docs/api/overview","draft":false,"unlisted":false,"editUrl":"https://github.com/willwade/tts-wrapper/tree/main/website/docs/api/overview.md","tags":[],"version":"current","frontMatter":{},"sidebar":"docs","previous":{"title":"Basic Usage","permalink":"/tts-wrapper/docs/guides/basic-usage"}},{"id":"guides/basic-usage","title":"Basic Usage","description":"This guide covers the fundamental operations of TTS Wrapper.","source":"@site/docs/guides/basic-usage.md","sourceDirName":"guides","slug":"/guides/basic-usage","permalink":"/tts-wrapper/docs/guides/basic-usage","draft":false,"unlisted":false,"editUrl":"https://github.com/willwade/tts-wrapper/tree/main/website/docs/guides/basic-usage.md","tags":[],"version":"current","frontMatter":{},"sidebar":"docs","previous":{"title":"quickstart","permalink":"/tts-wrapper/docs/quickstart"},"next":{"title":"API Overview","permalink":"/tts-wrapper/docs/api/overview"}},{"id":"installation","title":"installation","description":"","source":"@site/docs/installation.md","sourceDirName":".","slug":"/installation","permalink":"/tts-wrapper/docs/installation","draft":false,"unlisted":false,"editUrl":"https://github.com/willwade/tts-wrapper/tree/main/website/docs/installation.md","tags":[],"version":"current","frontMatter":{},"sidebar":"docs","previous":{"title":"Introduction","permalink":"/tts-wrapper/docs/intro"},"next":{"title":"quickstart","permalink":"/tts-wrapper/docs/quickstart"}},{"id":"intro","title":"Introduction","description":"TTS Wrapper is a powerful Python library that provides a unified interface for working with multiple Text-to-Speech (TTS) services. Whether you're using cloud-based services like AWS Polly, Google Cloud TTS, or local solutions like eSpeak, TTS Wrapper makes it easy to integrate and switch between different TTS engines.","source":"@site/docs/intro.md","sourceDirName":".","slug":"/intro","permalink":"/tts-wrapper/docs/intro","draft":false,"unlisted":false,"editUrl":"https://github.com/willwade/tts-wrapper/tree/main/website/docs/intro.md","tags":[],"version":"current","frontMatter":{},"sidebar":"docs","next":{"title":"installation","permalink":"/tts-wrapper/docs/installation"}},{"id":"quickstart","title":"quickstart","description":"","source":"@site/docs/quickstart.md","sourceDirName":".","slug":"/quickstart","permalink":"/tts-wrapper/docs/quickstart","draft":false,"unlisted":false,"editUrl":"https://github.com/willwade/tts-wrapper/tree/main/website/docs/quickstart.md","tags":[],"version":"current","frontMatter":{},"sidebar":"docs","previous":{"title":"installation","permalink":"/tts-wrapper/docs/installation"},"next":{"title":"Basic Usage","permalink":"/tts-wrapper/docs/guides/basic-usage"}}],"drafts":[],"sidebars":{"docs":[{"type":"category","label":"Getting Started","items":[{"type":"doc","id":"intro"},{"type":"doc","id":"installation"},{"type":"doc","id":"quickstart"}],"collapsed":true,"collapsible":true},{"type":"category","label":"Guides","items":[{"type":"doc","id":"guides/basic-usage"}],"collapsed":true,"collapsible":true},{"type":"category","label":"API Reference","items":[{"type":"doc","id":"api/overview"}],"collapsed":true,"collapsible":true}]}}]}},"docusaurus-plugin-content-pages":{"default":null},"docusaurus-plugin-debug":{},"docusaurus-plugin-svgr":{},"docusaurus-theme-classic":{},"docusaurus-bootstrap-plugin":{},"docusaurus-mdx-fallback-plugin":{}}}